{
  "_class": "group",
  "booleanOperation": -1,
  "clippingMaskMode": 0,
  "do_objectID": "2342B52E-B229-4566-B5AD-0845EB77ACF1",
  "exportOptions": {
    "_class": "exportOptions",
    "exportFormats": [
    ],
    "includedLayerIds": [
    ],
    "layerOptions": 0,
    "shouldTrim": false
  },
  "frame": {
    "_class": "rect",
    "constrainProportions": false,
    "do_objectID": "82B088C7-4F5A-4AF7-AE38-EC0B993D272D",
    "height": 37,
    "width": 258,
    "x": 59,
    "y": 135
  },
  "hasClickThrough": false,
  "hasClippingMask": false,
  "isFixedToViewport": false,
  "isFlippedHorizontal": false,
  "isFlippedVertical": false,
  "isLocked": false,
  "isVisible": true,
  "layerListExpandedType": 0,
  "layers": [
    {
      "class": "text",
      "id": "06908BD7-B6A2-4FD1-A7B0-A45FBC0238C7"
    },
    {
      "class": "rectangle",
      "id": "A5AF841C-6FBA-4482-BF93-DDB73B3A8B48"
    },
    {
      "class": "text",
      "id": "AC812294-6B3F-48B8-96EC-B741156608F8"
    }
  ],
  "name": "Group",
  "nameIsFixed": false,
  "resizingConstraint": 63,
  "resizingType": 0,
  "rotation": 0,
  "shouldBreakMaskChain": false,
  "style": {
    "_class": "style",
    "do_objectID": "7D0E4DA4-7A15-4329-8EC8-B39C994851E2",
    "endMarkerType": 0,
    "miterLimit": 10,
    "startMarkerType": 0,
    "windingRule": 1
  }
}