{
  "_class": "shapePath",
  "booleanOperation": -1,
  "clippingMaskMode": 0,
  "do_objectID": "8A29D985-61CD-4B6F-9BA7-25B441AA9C5E",
  "edited": true,
  "exportOptions": {
    "_class": "exportOptions",
    "exportFormats": [
    ],
    "includedLayerIds": [
    ],
    "layerOptions": 0,
    "shouldTrim": false
  },
  "frame": {
    "_class": "rect",
    "constrainProportions": false,
    "do_objectID": "06CC86BB-64AE-4317-B551-9211AD93FC35",
    "height": 7.904347826086958,
    "width": 9.221739130434782,
    "x": 0,
    "y": 0.3293478260869565
  },
  "hasClippingMask": false,
  "isClosed": true,
  "isFixedToViewport": false,
  "isFlippedHorizontal": false,
  "isFlippedVertical": false,
  "isLocked": false,
  "isVisible": true,
  "layerListExpandedType": 0,
  "name": "path17",
  "nameIsFixed": false,
  "pointRadiusBehaviour": 1,
  "points": [
    {
      "_class": "curvePoint",
      "cornerRadius": 0,
      "curveFrom": "{0.66949725200468502, 0}",
      "curveMode": 1,
      "curveTo": "{0.66949725200468502, 0}",
      "hasCurveFrom": false,
      "hasCurveTo": false,
      "point": "{0.66949725200468502, 0}"
    },
    {
      "_class": "curvePoint",
      "cornerRadius": 0,
      "curveFrom": "{0.0067798900801873674, 0}",
      "curveMode": 1,
      "curveTo": "{0.0067798900801873674, 0}",
      "hasCurveFrom": false,
      "hasCurveTo": false,
      "point": "{0.0067798900801873674, 0}"
    },
    {
      "_class": "curvePoint",
      "cornerRadius": 0,
      "curveFrom": "{0.51696098747634922, 0.18980987802023455}",
      "curveMode": 4,
      "curveTo": "{0, 0.03716611615386612}",
      "hasCurveFrom": true,
      "hasCurveTo": false,
      "point": "{0, 0.03716611615386612}"
    },
    {
      "_class": "curvePoint",
      "cornerRadius": 0,
      "curveFrom": "{1, 1}",
      "curveMode": 4,
      "curveTo": "{0.85933417424993253, 0.55775182709563309}",
      "hasCurveFrom": false,
      "hasCurveTo": true,
      "point": "{1, 1}"
    },
    {
      "_class": "curvePoint",
      "cornerRadius": 0,
      "curveFrom": "{0.83221461392918283, 0.037140107675102105}",
      "curveMode": 4,
      "curveTo": "{0.85593296693395804, 0.15462040625243831}",
      "hasCurveFrom": true,
      "hasCurveTo": false,
      "point": "{0.85593296693395804, 0.15462040625243831}"
    },
    {
      "_class": "curvePoint",
      "cornerRadius": 0,
      "curveFrom": "{0.66949725200468502, 0}",
      "curveMode": 4,
      "curveTo": "{0.75932516442922782, 0.0038752633358475103}",
      "hasCurveFrom": false,
      "hasCurveTo": true,
      "point": "{0.66949725200468502, 0}"
    }
  ],
  "resizingConstraint": 63,
  "resizingType": 0,
  "rotation": 0,
  "shouldBreakMaskChain": false,
  "style": {
    "_class": "style",
    "blur": {
      "_class": "blur",
      "center": "{0.5, 0.5}",
      "do_objectID": "FF712EBC-DBA4-464B-A243-F3242D397DAB",
      "isEnabled": false,
      "motionAngle": 0,
      "radius": 44.29963100000001,
      "saturation": 1,
      "type": 0
    },
    "do_objectID": "00A3C0D7-23D9-4673-948A-FFF51C73E72E",
    "endMarkerType": 0,
    "fills": [
      {
        "_class": "fill",
        "color": {
          "_class": "color",
          "alpha": 1,
          "blue": 0.1019607843137255,
          "green": 0.6509803921568628,
          "red": 0.9803921568627451
        },
        "fillType": 0,
        "isEnabled": true,
        "noiseIndex": 0,
        "noiseIntensity": 0,
        "patternFillType": 1,
        "patternTileScale": 1
      }
    ],
    "miterLimit": 10,
    "startMarkerType": 0,
    "windingRule": 1
  }
}