{
  "_class": "group",
  "booleanOperation": -1,
  "clippingMaskMode": 0,
  "do_objectID": "6556EA93-1E99-439B-BF3A-0FB33D67632D",
  "exportOptions": {
    "_class": "exportOptions",
    "do_objectID": "76FA1D72-3B4B-4AFC-AE6A-F2971BDF997E",
    "exportFormats": [
      {
        "_class": "exportFormat",
        "absoluteSize": 0,
        "fileFormat": "png",
        "name": "",
        "namingScheme": 0,
        "scale": 1,
        "visibleScaleType": 0
      }
    ],
    "includedLayerIds": [
    ],
    "layerOptions": 0,
    "shouldTrim": false
  },
  "frame": {
    "_class": "rect",
    "constrainProportions": false,
    "do_objectID": "B8A44B93-83E8-4ABE-BC20-6BE1EA050083",
    "height": 48,
    "width": 350,
    "x": 738,
    "y": 346
  },
  "hasClickThrough": false,
  "hasClippingMask": false,
  "isFixedToViewport": false,
  "isFlippedHorizontal": false,
  "isFlippedVertical": false,
  "isLocked": false,
  "isVisible": true,
  "layerListExpandedType": 0,
  "layers": [
    {
      "class": "rectangle",
      "id": "0DC94713-05F0-43AE-8CE5-831A00869B4B"
    },
    {
      "class": "text",
      "id": "E60ED937-951E-4C4D-87BA-67BD98CED95F"
    }
  ],
  "name": "Group 2",
  "nameIsFixed": false,
  "resizingConstraint": 63,
  "resizingType": 0,
  "rotation": 0,
  "shouldBreakMaskChain": false,
  "style": {
    "_class": "style",
    "do_objectID": "5154E717-46A5-42CA-A8BD-EEAACADFCFB7",
    "endMarkerType": 0,
    "miterLimit": 10,
    "startMarkerType": 0,
    "windingRule": 1
  },
  "userInfo": {
    "com.invision.prototype": {
      "backgroundOpacity": 0,
      "closeOnClickOutside": 1,
      "componentType": "SRLink",
      "fixOverlayPosition": 1,
      "gesture": 0,
      "linkType": 0,
      "maintainScrollPositionAfterGesture": 0,
      "maintainScrollPositionAfterRedirect": 0,
      "openURLInNewWindow": 0,
      "overlayPosition": 0,
      "overlayTransition": 0,
      "redirectAfter": 0,
      "reverseTransitionOnClose": 1,
      "scrollToPosition": 0,
      "smoothScrolling": 0,
      "stayOnTargetScreen": 0,
      "targetArtboardID": "94052962-357F-4D76-BBFA-8D0CF93307CE",
      "transition": 0
    }
  }
}