{
  "_class": "symbolInstance",
  "booleanOperation": -1,
  "clippingMaskMode": 0,
  "do_objectID": "69FD0B95-571A-46E5-A3B3-26060B1C1A8F",
  "exportOptions": {
    "_class": "exportOptions",
    "exportFormats": [
    ],
    "includedLayerIds": [
    ],
    "layerOptions": 0,
    "shouldTrim": false
  },
  "frame": {
    "_class": "rect",
    "constrainProportions": false,
    "do_objectID": "07DB1480-CBED-483E-9085-2941C2A5F76B",
    "height": 20,
    "width": 20,
    "x": 0,
    "y": 1
  },
  "hasClippingMask": false,
  "horizontalSpacing": 0,
  "isFixedToViewport": false,
  "isFlippedHorizontal": false,
  "isFlippedVertical": false,
  "isLocked": false,
  "isVisible": true,
  "layerListExpandedType": 0,
  "name": "radio-buttom-none",
  "nameIsFixed": false,
  "overrideValues": [
  ],
  "resizingConstraint": 63,
  "resizingType": 0,
  "rotation": 0,
  "scale": 1,
  "shouldBreakMaskChain": false,
  "style": {
    "_class": "style",
    "do_objectID": "D24B3A52-A82E-4B5C-975B-A633EBFE0667",
    "endMarkerType": 0,
    "miterLimit": 10,
    "startMarkerType": 0,
    "windingRule": 1
  },
  "symbolID": "CC2029FA-3368-4C39-B5F5-3B751807B513",
  "verticalSpacing": 0
}