{
  "_class": "shapePath",
  "booleanOperation": -1,
  "clippingMaskMode": 0,
  "do_objectID": "D334ABEA-BA82-4F5C-9A27-A711AA21D10E",
  "edited": true,
  "exportOptions": {
    "_class": "exportOptions",
    "exportFormats": [
    ],
    "includedLayerIds": [
    ],
    "layerOptions": 0,
    "shouldTrim": false
  },
  "frame": {
    "_class": "rect",
    "constrainProportions": false,
    "do_objectID": "56C5874C-BB89-4B26-A1B2-6D854D862480",
    "height": 19.03615999999996,
    "width": 42.26681904761875,
    "x": 266.5910857142861,
    "y": 48.58538666666683
  },
  "hasClippingMask": false,
  "isClosed": true,
  "isFixedToViewport": false,
  "isFlippedHorizontal": false,
  "isFlippedVertical": false,
  "isLocked": false,
  "isVisible": true,
  "layerListExpandedType": 0,
  "name": "Path",
  "nameIsFixed": false,
  "pointRadiusBehaviour": 1,
  "points": [
    {
      "_class": "curvePoint",
      "cornerRadius": 0,
      "curveFrom": "{0.04476234425472983, 0.59467455621301735}",
      "curveMode": 4,
      "curveTo": "{0, 0}",
      "hasCurveFrom": true,
      "hasCurveTo": false,
      "point": "{0, 0}"
    },
    {
      "_class": "curvePoint",
      "cornerRadius": 0,
      "curveFrom": "{0.78218735579141607, 1}",
      "curveMode": 3,
      "curveTo": "{0.21365943700969045, 1}",
      "hasCurveFrom": true,
      "hasCurveTo": true,
      "point": "{0.51222888786340537, 1}"
    },
    {
      "_class": "curvePoint",
      "cornerRadius": 0,
      "curveFrom": "{1, 0}",
      "curveMode": 4,
      "curveTo": "{0.95569912321181349, 0.63806706114398426}",
      "hasCurveFrom": false,
      "hasCurveTo": true,
      "point": "{1, 0}"
    }
  ],
  "resizingConstraint": 63,
  "resizingType": 0,
  "rotation": 0,
  "shouldBreakMaskChain": false,
  "style": {
    "_class": "style",
    "blur": {
      "_class": "blur",
      "center": "{0.5, 0.5}",
      "do_objectID": "36DE070D-A4BC-4214-9426-84C69F5D9EB3",
      "isEnabled": false,
      "motionAngle": 0,
      "radius": 39.29625,
      "saturation": 1,
      "type": 0
    },
    "do_objectID": "9D3D9DB4-E12D-45A3-B8D8-8A5B95FBA57B",
    "endMarkerType": 0,
    "miterLimit": 10,
    "startMarkerType": 0,
    "windingRule": 1
  }
}